tekigo/__init__.py
tekigo/base.py
tekigo/front.py
tekigo/hipster.py
tekigo/tekigosol.py
tekigo/tkg_logging.py
tekigo/tools.py
tekigo/scripts/__init__.py
tekigo/scripts/teki_indirect_adaptation.py
tekigo-1.1.2.dist-info/licenses/LICENSE.txt
tekigo-1.1.2.dist-info/METADATA
tekigo-1.1.2.dist-info/WHEEL
tekigo-1.1.2.dist-info/top_level.txt
tekigo-1.1.2.dist-info/RECORD
