Metadata-Version: 2.4
Name: tekigo
Version: 1.1.2
Summary: Cerfacs mesh adaption toolkit
Author-email: CoopTeam-CERFACS <coop@cerfacs.fr>
License: Copyright (c) 2021 Cerfacs/COOP Team
Project-URL: Homepage, https://gitlab.com/cerfacs/tekigo
Project-URL: Documentation, https://tekigo.readthedocs.io/en/latest/
Project-URL: Issues, https://gitlab.com/cerfacs/tekigo/-/issues
Keywords: tekigo API
Classifier: Programming Language :: Python :: 3.7
Classifier: Programming Language :: Python :: 3.8
Classifier: Programming Language :: Python :: 3.9
Classifier: Programming Language :: Python :: 3.10
Classifier: Programming Language :: Python :: 3.11
Classifier: Programming Language :: Python :: 3.12
Classifier: Programming Language :: Python :: 3.13
Requires-Python: >=3.7
License-File: LICENSE.txt
Requires-Dist: numpy
Requires-Dist: scipy
Requires-Dist: h5py
Requires-Dist: loguru
Requires-Dist: pyhip
Requires-Dist: pyyaml
Provides-Extra: tests
Requires-Dist: pytest; extra == "tests"
Requires-Dist: pytest-coverage; extra == "tests"
Requires-Dist: h5cross; extra == "tests"
Requires-Dist: matplotlib; extra == "tests"
Provides-Extra: docs
Requires-Dist: sphinx_rtd_theme; extra == "docs"
Requires-Dist: recommonmark; extra == "docs"
Dynamic: license-file
